sdc_rabbit-1.7.0-py3.6-nspkg.pth
sdc/rabbit/__init__.py
sdc/rabbit/consumers.py
sdc/rabbit/exceptions.py
sdc/rabbit/publishers.py
sdc/rabbit/test/__init__.py
sdc/rabbit/test/receipt_404.xml
sdc/rabbit/test/receipt_incorrect_ru_ce.xml
sdc/rabbit/test/test_consumer.py
sdc/rabbit/test/test_data.py
sdc/rabbit/test/test_publisher.py
sdc_rabbit-1.7.0.dist-info/LICENSE
sdc_rabbit-1.7.0.dist-info/METADATA
sdc_rabbit-1.7.0.dist-info/WHEEL
sdc_rabbit-1.7.0.dist-info/entry_points.txt
sdc_rabbit-1.7.0.dist-info/namespace_packages.txt
sdc_rabbit-1.7.0.dist-info/top_level.txt
sdc_rabbit-1.7.0.dist-info/RECORD
