Metadata-Version: 2.1
Name: sdc-rabbit
Version: 1.7.0
Summary: A shared library for SDC services that interact with RabbitMQ using Pika
Home-page: https://github.com/ONSdigital/sdc-rabbit
Author: J Gardiner
Author-email: james@jgardiner.co.uk
License: UNKNOWN
Platform: UNKNOWN
Classifier: Operating System :: OS Independent
Classifier: Programming Language :: Python :: 3.4
Classifier: Programming Language :: Python :: 3.5
Classifier: Programming Language :: Python :: 3.6
Classifier: Programming Language :: Python :: 3.7
Classifier: License :: OSI Approved :: MIT License
Requires-Dist: pika (>=1.0)
Requires-Dist: structlog (>=17.2.0)
Requires-Dist: tornado (>=4.5.1)
